odoo/addons/sale_require_po_doc/README.rst
odoo/addons/sale_require_po_doc/__init__.py
odoo/addons/sale_require_po_doc/__manifest__.py
odoo/addons/sale_require_po_doc/i18n/sale_require_po_doc.pot
odoo/addons/sale_require_po_doc/models/__init__.py
odoo/addons/sale_require_po_doc/models/res_partner.py
odoo/addons/sale_require_po_doc/models/sale_order.py
odoo/addons/sale_require_po_doc/readme/CONTRIBUTORS.rst
odoo/addons/sale_require_po_doc/readme/CREDITS.rst
odoo/addons/sale_require_po_doc/readme/DESCRIPTION.rst
odoo/addons/sale_require_po_doc/static/description/icon.png
odoo/addons/sale_require_po_doc/static/description/index.html
odoo/addons/sale_require_po_doc/views/res_partner_view.xml
odoo/addons/sale_require_po_doc/views/sale_order_view.xml
odoo14_addon_sale_require_po_doc-14.0.1.0.1.dist-info/METADATA
odoo14_addon_sale_require_po_doc-14.0.1.0.1.dist-info/WHEEL
odoo14_addon_sale_require_po_doc-14.0.1.0.1.dist-info/top_level.txt
odoo14_addon_sale_require_po_doc-14.0.1.0.1.dist-info/RECORD
